GDALHelper/color_ramp_hsv.py
GDALHelper/gdal_helper.py
GDALHelper/git_utils.py
GDALHelper/helper_commands.py
gdalhelper-1.2.3.dist-info/licenses/LICENSE
tests/test_adjust_hsv.py
tests/test_set_version.py
gdalhelper-1.2.3.dist-info/METADATA
gdalhelper-1.2.3.dist-info/WHEEL
gdalhelper-1.2.3.dist-info/entry_points.txt
gdalhelper-1.2.3.dist-info/top_level.txt
gdalhelper-1.2.3.dist-info/RECORD
