Metadata-Version: 2.4
Name: GDALHelper
Version: 1.2.3
Summary: A collection of helper utilities for GDAL
Author: corb
License: MIT License
Project-URL: Repository, https://github.com/corb555/Gdal-helper
Keywords: GDAL,GIS,DEM,Elevation,workflow
Classifier: Topic :: Scientific/Engineering :: GIS
Classifier: License :: OSI Approved :: MIT License
Classifier: Programming Language :: Python :: 3
Classifier: Programming Language :: Python :: 3.9
Classifier: Programming Language :: Python :: 3.10
Classifier: Programming Language :: Python :: 3.11
Requires-Python: >=3.9
License-File: LICENSE
Dynamic: license-file
